python_ripgrep-0.0.9.dist-info/METADATA
python_ripgrep-0.0.9.dist-info/WHEEL
python_ripgrep-0.0.9.dist-info/licenses/LICENSE
python_ripgrep/__init__.py
python_ripgrep/__init__.pyi
python_ripgrep/py.typed
python_ripgrep/python_ripgrep.abi3.so
python_ripgrep-0.0.9.dist-info/RECORD
